uighur_reshaper/__init__.py
uighur_reshaper/shaper.py
uighur_reshaper/test.py
uighur_reshaper-0.1.1.dist-info/METADATA
uighur_reshaper-0.1.1.dist-info/WHEEL
uighur_reshaper-0.1.1.dist-info/entry_points.txt
uighur_reshaper-0.1.1.dist-info/top_level.txt
uighur_reshaper-0.1.1.dist-info/RECORD
