Metadata-Version: 2.1
Name: uighur_reshaper
Version: 0.1.1
Summary: 一个用于维吾尔语文本转换扩展区的Python工具
Home-page: https://github.com/Sulayman/uighur_reshaper
Author: Sulayman
Author-email: Sulayman@eotor.net
Keywords: 维吾尔语文本转扩展区
Classifier: Development Status :: 3 - Alpha
Classifier: Intended Audience :: Developers
Classifier: Topic :: Software Development :: Build Tools
Classifier: License :: OSI Approved :: MIT License
Classifier: Programming Language :: Python :: 3
Classifier: Programming Language :: Python :: 3.7
Classifier: Programming Language :: Python :: 3.8
Requires-Python: >=3.6
